my_package_sstock/__init__.py
my_package_sstock/safety_stock.py
my_package_sstock-0.1.dist-info/METADATA
my_package_sstock-0.1.dist-info/WHEEL
my_package_sstock-0.1.dist-info/top_level.txt
my_package_sstock-0.1.dist-info/RECORD
